hydro_model_builder/__init__.py
hydro_model_builder/cli.py
hydro_model_builder/datahandler.py
hydro_model_builder/model_builder.py
hydro_model_builder/model_generator.py
hydro_model_builder-0.0.7.dist-info/METADATA
hydro_model_builder-0.0.7.dist-info/RECORD
hydro_model_builder-0.0.7.dist-info/WHEEL
hydro_model_builder-0.0.7.dist-info/entry_points.txt
hydro_model_builder-0.0.7.dist-info/top_level.txt
