Metadata-Version: 2.1
Name: hydro-model-builder
Version: 0.0.7
Summary: Python package for the generation of water-related models
Home-page: https://github.com/gena/hydro_model_builder
Author: Gennadii Donchyts
Author-email: gennadiy.donchyts@gmail.com
License: MIT license
Keywords: hydro_model_builder
Platform: UNKNOWN
Classifier: Development Status :: 2 - Pre-Alpha
Classifier: Intended Audience :: Developers
Classifier: License :: OSI Approved :: MIT License
Classifier: Natural Language :: English
Classifier: Programming Language :: Python :: 2
Classifier: Programming Language :: Python :: 2.7
Classifier: Programming Language :: Python :: 3
Classifier: Programming Language :: Python :: 3.4
Classifier: Programming Language :: Python :: 3.5
Classifier: Programming Language :: Python :: 3.6
Requires-Dist: Click (>=6.0)
